trinsic/__init__.py
trinsic/__main__.py
trinsic/access_management_service.py
trinsic/connect_service.py
trinsic/credential_service.py
trinsic/file_management_service.py
trinsic/provider_service.py
trinsic/service_base.py
trinsic/template_service.py
trinsic/trinsic_service.py
trinsic/trinsic_util.py
trinsic/trustregistry_service.py
trinsic/wallet_service.py
trinsic/proto/__init__.py
trinsic/proto/google/__init__.py
trinsic/proto/google/api/__init__.py
trinsic/proto/sdk/__init__.py
trinsic/proto/sdk/options/__init__.py
trinsic/proto/sdk/options/v1/__init__.py
trinsic/proto/services/__init__.py
trinsic/proto/services/account/__init__.py
trinsic/proto/services/account/v1/__init__.py
trinsic/proto/services/common/__init__.py
trinsic/proto/services/common/v1/__init__.py
trinsic/proto/services/connect/__init__.py
trinsic/proto/services/connect/v1/__init__.py
trinsic/proto/services/filemanagement/__init__.py
trinsic/proto/services/filemanagement/v1/__init__.py
trinsic/proto/services/options/__init__.py
trinsic/proto/services/provider/__init__.py
trinsic/proto/services/provider/v1/__init__.py
trinsic/proto/services/trustregistry/__init__.py
trinsic/proto/services/trustregistry/v1/__init__.py
trinsic/proto/services/universalwallet/__init__.py
trinsic/proto/services/universalwallet/v1/__init__.py
trinsic/proto/services/verifiablecredentials/__init__.py
trinsic/proto/services/verifiablecredentials/templates/__init__.py
trinsic/proto/services/verifiablecredentials/templates/v1/__init__.py
trinsic/proto/services/verifiablecredentials/v1/__init__.py
trinsic_sdk-1.14.0.dist-info/METADATA
trinsic_sdk-1.14.0.dist-info/WHEEL
trinsic_sdk-1.14.0.dist-info/top_level.txt
trinsic_sdk-1.14.0.dist-info/RECORD
