Metadata-Version: 2.1
Name: trinsic-sdk
Version: 1.14.0
Summary: Trinsic Services SDK bindings
Home-page: https://github.com/trinsic-id/okapi/
Author: Scott Phillips
Author-email: scott.phillips@trinsic.id
Project-URL: Bug Tracker, https://github.com/trinsic-id/okapi/issues
Classifier: Programming Language :: Python :: 3
Classifier: License :: OSI Approved :: Apache Software License
Classifier: Operating System :: OS Independent
Requires-Python: >=3.8
Requires-Dist: grpclib >=0.4.3rc2
Requires-Dist: betterproto >=2.0.0b4
Requires-Dist: deprecation >=2.1.0
